 [
   {
      "name":"Lone Star",
      "url":"/lone-star/",
      "desc":"Playing with lines and randomness using p5.js and canvas API. Yet another attempt to _Code like no one's watching_"
   },
   {
      "name":"Badgee",
      "url":"https://github.com/dharFr/badgee/",
      "desc":"A browser console improvement"
   },
   {
      "name":"The Way We Move",
      "url":"/the-way-we-move/",
      "desc":"Let's play with canvas drawing and WebAudio API, see if something interesting might appear. A first attempt to Code like no one's watching."
   },
   {
      "name":"Testing Dailymotion Video Player",
      "url":"/Test-page-Dailymotion-Video-Player/",
      "desc":"A basic test page for Dailymotion Video Player"
   }
]